[
  {
    "id": "1",
    "type":"Self-Perception",
    "question": "How would you describe yourself in one word?"
  },
  {
    "id":"2",
    "type":"Self-Perception",
    "question":"Tell me one strength, and one weakness of yours?"
  },
  {
    "id":"3",
    "type":"Self-Perception",
    "question":"What can you offer us that someone else can not?"
  },
  {
    "id":"4",
    "type":"Self-Perception",
    "question":"What's the one thing your former manager would like you to improvw on?"
  },
  {
    "id":"5",
    "type":"Self-Perception",
    "question":"Tell me about an accomplishment you are most proud of."
  },
  {
    "id":"6",
    "type":"Self-Expression",
    "question":"Give a time when you went above and beyond the requirements for a project."
  },
  {
    "id":"7",
    "type":"Self-Expression",
    "question":"Tell me about a time that you disagree with a rule or approach."
  },
  {
    "id":"8",
    "type":"Self-Expression",
    "question":"Tell me about a time you stepped up and lead with an idea you had?"
  },
  {
    "id":"9",
    "type":"Interpersonal",
    "question":"What kind of boss and coworkers have you had the most and least success with, and why?"
  },
  {
    "id":"10",
    "type":"Interpersonal",
    "question":"Can you give us a reason someone may not like working with you?"
  },
  {
    "id":"11",
    "type":"Interpersonal",
    "question":"Tell me about a tetam project when you had to work with someone difficult."
  },
  {
    "id":"12",
    "type":"Decison Making",
    "question":"Why do you want to leave your current job?"
  },
  {
    "id":"13",
    "type":"Decison Making",
    "question":"What do you like most about working in this industry?"
  },
  {
    "id":"14",
    "type":"Decison Making",
    "question":"Do you usually make better decisions alone or with a group? Why? When do you ask for help?"
  },
  {
    "id":"15",
    "type":"Stress Management",
    "question":"Tell me how you handled a diddicult situation."
  },
  {
    "id":"16",
    "type":"Stress Management",
    "question":"Tell me about a time you made a mistake."
  },
  {
    "id":"17",
    "type":"Stress Management",
    "question":"What would you look to accomplish in the first 30,60, or 90 days on the job?"
  },
  {
    "id":"18",
    "type":"Stress Management",
    "question":"What do like the most and least about working in the industry?"
  },
  {
    "id":"19",
    "type":"Motivators",
    "question":"Where do you see yourself five to ten years?"
  },
  {
    "id":"20",
    "type":"Motivators",
    "question":"What is your dream job?"
  },
  {
    "id":"21",
    "type":"Motivators",
    "question":"Why are you looking a new job?"
  },
  {
    "id":"22",
    "type":"Motivators",
    "question":"Why do you want to work here?"
  },
  {
    "id":"23",
    "type":"Motivators",
    "question":"What motivates/gets you up in the morning?"
  },
  {
    "id":"24",
    "type":"General Questions",
    "question":"Tell me about your educational background."
  },
  {
    "id":"25",
    "type":"General Questions",
    "question":"How did you heat about this position?"
  },
  {
    "id":"26",
    "type":"General Questions",
    "question":"What are your salary requirements?"
  },
  {
    "id":"27",
    "type":"General Questions",
    "question":"Qestions to ask interviewer"
  }
]

